pytrxmat/__init__.py
pytrxmat/repository.py
pytrxmat/trx.py
pytrxmat-0.0.5.dist-info/LICENSE
pytrxmat-0.0.5.dist-info/METADATA
pytrxmat-0.0.5.dist-info/WHEEL
pytrxmat-0.0.5.dist-info/top_level.txt
pytrxmat-0.0.5.dist-info/RECORD
